{
  "annotations": {
    "list": [
      {
        "builtIn": 1,
        "datasource": "-- Grafana --",
        "enable": true,
        "hide": true,
        "iconColor": "rgba(0, 211, 255, 1)",
        "name": "Annotations & Alerts",
        "type": "dashboard"
      }
    ]
  },
  "editable": true,
  "gnetId": null,
  "graphTooltip": 0,
  "links": [],
  "panels": [
    {
      "aliasColors": {},
      "id": 609,
      "bars": false,
      "dashLength": 10,
      "dashes": false,
      "datasource": null,
      "fieldConfig": {
        "defaults": {
          "custom": {}
        },
        "overrides": []
      },
      "fill": 1,
      "fillGradient": 0,
      "hiddenSeries": false,
      "legend": {
        "avg": false,
        "current": false,
        "max": false,
        "min": false,
        "show": true,
        "total": false,
        "values": false
      },
      "lines": true,
      "linewidth": 1,
      "nullPointMode": "null",
      "options": {
        "alertThreshold": true
      },
      "percentage": false,
      "pluginVersion": "7.3.3",
      "pointradius": 2,
      "points": false,
      "renderer": "flot",
      "seriesOverrides": [],
      "spaceLength": 10,
      "stack": false,
      "steppedLine": false,
      "description": "consume_service",
      "gridPos": {
        "h": 9,
        "w": 12
      },
      "targets": [
        {
          "expr": "kafka_monitor_commit_latency_service_consume_service_commit_offset_latency_ms_9999th",
          "interval": "",
          "legendFormat": "commit_offset_latency_ms_9999th",
          "refId": "MhE"
        }
      ],
      "title": "commit_latency_service",
      "thresholds": [],
      "timeFrom": null,
      "timeRegions": [],
      "timeShift": null,
      "tooltip": {
        "shared": true,
        "sort": 0,
        "value_type": "individual"
      },
      "xaxis": {
        "buckets": null,
        "mode": "time",
        "name": null,
        "show": true,
        "values": []
      },
      "yaxis": {
        "align": false,
        "alignLevel": null
      },
      "type": "graph"
    },
    {
      "aliasColors": {},
      "id": 159,
      "bars": false,
      "dashLength": 10,
      "dashes": false,
      "datasource": null,
      "fieldConfig": {
        "defaults": {
          "custom": {}
        },
        "overrides": []
      },
      "fill": 1,
      "fillGradient": 0,
      "hiddenSeries": false,
      "legend": {
        "avg": false,
        "current": false,
        "max": false,
        "min": false,
        "show": true,
        "total": false,
        "values": false
      },
      "lines": true,
      "linewidth": 1,
      "nullPointMode": "null",
      "options": {
        "alertThreshold": true
      },
      "percentage": false,
      "pluginVersion": "7.3.3",
      "pointradius": 2,
      "points": false,
      "renderer": "flot",
      "seriesOverrides": [],
      "spaceLength": 10,
      "stack": false,
      "steppedLine": false,
      "description": "consume_service",
      "gridPos": {
        "h": 9,
        "w": 12
      },
      "targets": [
        {
          "expr": "kafka_monitor_commit_latency_service_consume_service_commit_offset_latency_ms_999th",
          "interval": "",
          "legendFormat": "commit_offset_latency_ms_999th",
          "refId": "SBU"
        }
      ],
      "title": "commit_latency_service",
      "thresholds": [],
      "timeFrom": null,
      "timeRegions": [],
      "timeShift": null,
      "tooltip": {
        "shared": true,
        "sort": 0,
        "value_type": "individual"
      },
      "xaxis": {
        "buckets": null,
        "mode": "time",
        "name": null,
        "show": true,
        "values": []
      },
      "yaxis": {
        "align": false,
        "alignLevel": null
      },
      "type": "graph"
    },
    {
      "aliasColors": {},
      "id": 535,
      "bars": false,
      "dashLength": 10,
      "dashes": false,
      "datasource": null,
      "fieldConfig": {
        "defaults": {
          "custom": {}
        },
        "overrides": []
      },
      "fill": 1,
      "fillGradient": 0,
      "hiddenSeries": false,
      "legend": {
        "avg": false,
        "current": false,
        "max": false,
        "min": false,
        "show": true,
        "total": false,
        "values": false
      },
      "lines": true,
      "linewidth": 1,
      "nullPointMode": "null",
      "options": {
        "alertThreshold": true
      },
      "percentage": false,
      "pluginVersion": "7.3.3",
      "pointradius": 2,
      "points": false,
      "renderer": "flot",
      "seriesOverrides": [],
      "spaceLength": 10,
      "stack": false,
      "steppedLine": false,
      "description": "consume_service",
      "gridPos": {
        "h": 9,
        "w": 12
      },
      "targets": [
        {
          "expr": "kafka_monitor_commit_latency_service_consume_service_commit_offset_latency_ms_99th",
          "interval": "",
          "legendFormat": "commit_offset_latency_ms_99th",
          "refId": "Cnq"
        }
      ],
      "title": "commit_latency_service",
      "thresholds": [],
      "timeFrom": null,
      "timeRegions": [],
      "timeShift": null,
      "tooltip": {
        "shared": true,
        "sort": 0,
        "value_type": "individual"
      },
      "xaxis": {
        "buckets": null,
        "mode": "time",
        "name": null,
        "show": true,
        "values": []
      },
      "yaxis": {
        "align": false,
        "alignLevel": null
      },
      "type": "graph"
    },
    {
      "aliasColors": {},
      "id": 685,
      "bars": false,
      "dashLength": 10,
      "dashes": false,
      "datasource": null,
      "fieldConfig": {
        "defaults": {
          "custom": {}
        },
        "overrides": []
      },
      "fill": 1,
      "fillGradient": 0,
      "hiddenSeries": false,
      "legend": {
        "avg": false,
        "current": false,
        "max": false,
        "min": false,
        "show": true,
        "total": false,
        "values": false
      },
      "lines": true,
      "linewidth": 1,
      "nullPointMode": "null",
      "options": {
        "alertThreshold": true
      },
      "percentage": false,
      "pluginVersion": "7.3.3",
      "pointradius": 2,
      "points": false,
      "renderer": "flot",
      "seriesOverrides": [],
      "spaceLength": 10,
      "stack": false,
      "steppedLine": false,
      "description": "consume_service",
      "gridPos": {
        "h": 9,
        "w": 12
      },
      "targets": [
        {
          "expr": "kafka_monitor_commit_latency_service_consume_service_commit_offset_latency_ms_avg",
          "interval": "",
          "legendFormat": "commit_offset_latency_ms_avg",
          "refId": "Eek"
        }
      ],
      "title": "commit_latency_service",
      "thresholds": [],
      "timeFrom": null,
      "timeRegions": [],
      "timeShift": null,
      "tooltip": {
        "shared": true,
        "sort": 0,
        "value_type": "individual"
      },
      "xaxis": {
        "buckets": null,
        "mode": "time",
        "name": null,
        "show": true,
        "values": []
      },
      "yaxis": {
        "align": false,
        "alignLevel": null
      },
      "type": "graph"
    },
    {
      "aliasColors": {},
      "id": 143,
      "bars": false,
      "dashLength": 10,
      "dashes": false,
      "datasource": null,
      "fieldConfig": {
        "defaults": {
          "custom": {}
        },
        "overrides": []
      },
      "fill": 1,
      "fillGradient": 0,
      "hiddenSeries": false,
      "legend": {
        "avg": false,
        "current": false,
        "max": false,
        "min": false,
        "show": true,
        "total": false,
        "values": false
      },
      "lines": true,
      "linewidth": 1,
      "nullPointMode": "null",
      "options": {
        "alertThreshold": true
      },
      "percentage": false,
      "pluginVersion": "7.3.3",
      "pointradius": 2,
      "points": false,
      "renderer": "flot",
      "seriesOverrides": [],
      "spaceLength": 10,
      "stack": false,
      "steppedLine": false,
      "description": "consume_service",
      "gridPos": {
        "h": 9,
        "w": 12
      },
      "targets": [
        {
          "expr": "kafka_monitor_commit_latency_service_consume_service_commit_offset_latency_ms_max",
          "interval": "",
          "legendFormat": "commit_offset_latency_ms_max",
          "refId": "MCp"
        }
      ],
      "title": "commit_latency_service",
      "thresholds": [],
      "timeFrom": null,
      "timeRegions": [],
      "timeShift": null,
      "tooltip": {
        "shared": true,
        "sort": 0,
        "value_type": "individual"
      },
      "xaxis": {
        "buckets": null,
        "mode": "time",
        "name": null,
        "show": true,
        "values": []
      },
      "yaxis": {
        "align": false,
        "alignLevel": null
      },
      "type": "graph"
    },
    {
      "aliasColors": {},
      "id": 81,
      "bars": false,
      "dashLength": 10,
      "dashes": false,
      "datasource": null,
      "fieldConfig": {
        "defaults": {
          "custom": {}
        },
        "overrides": []
      },
      "fill": 1,
      "fillGradient": 0,
      "hiddenSeries": false,
      "legend": {
        "avg": false,
        "current": false,
        "max": false,
        "min": false,
        "show": true,
        "total": false,
        "values": false
      },
      "lines": true,
      "linewidth": 1,
      "nullPointMode": "null",
      "options": {
        "alertThreshold": true
      },
      "percentage": false,
      "pluginVersion": "7.3.3",
      "pointradius": 2,
      "points": false,
      "renderer": "flot",
      "seriesOverrides": [],
      "spaceLength": 10,
      "stack": false,
      "steppedLine": false,
      "description": "single_cluster_monitor",
      "gridPos": {
        "h": 9,
        "w": 12
      },
      "targets": [
        {
          "expr": "kafka_monitor_commit_latency_service_single_cluster_monitor_commit_offset_latency_ms_9999th",
          "interval": "",
          "legendFormat": "commit_offset_latency_ms_9999th",
          "refId": "rjw"
        }
      ],
      "title": "commit_latency_service",
      "thresholds": [],
      "timeFrom": null,
      "timeRegions": [],
      "timeShift": null,
      "tooltip": {
        "shared": true,
        "sort": 0,
        "value_type": "individual"
      },
      "xaxis": {
        "buckets": null,
        "mode": "time",
        "name": null,
        "show": true,
        "values": []
      },
      "yaxis": {
        "align": false,
        "alignLevel": null
      },
      "type": "graph"
    },
    {
      "aliasColors": {},
      "id": 596,
      "bars": false,
      "dashLength": 10,
      "dashes": false,
      "datasource": null,
      "fieldConfig": {
        "defaults": {
          "custom": {}
        },
        "overrides": []
      },
      "fill": 1,
      "fillGradient": 0,
      "hiddenSeries": false,
      "legend": {
        "avg": false,
        "current": false,
        "max": false,
        "min": false,
        "show": true,
        "total": false,
        "values": false
      },
      "lines": true,
      "linewidth": 1,
      "nullPointMode": "null",
      "options": {
        "alertThreshold": true
      },
      "percentage": false,
      "pluginVersion": "7.3.3",
      "pointradius": 2,
      "points": false,
      "renderer": "flot",
      "seriesOverrides": [],
      "spaceLength": 10,
      "stack": false,
      "steppedLine": false,
      "description": "single_cluster_monitor",
      "gridPos": {
        "h": 9,
        "w": 12
      },
      "targets": [
        {
          "expr": "kafka_monitor_commit_latency_service_single_cluster_monitor_commit_offset_latency_ms_999th",
          "interval": "",
          "legendFormat": "commit_offset_latency_ms_999th",
          "refId": "Rgt"
        }
      ],
      "title": "commit_latency_service",
      "thresholds": [],
      "timeFrom": null,
      "timeRegions": [],
      "timeShift": null,
      "tooltip": {
        "shared": true,
        "sort": 0,
        "value_type": "individual"
      },
      "xaxis": {
        "buckets": null,
        "mode": "time",
        "name": null,
        "show": true,
        "values": []
      },
      "yaxis": {
        "align": false,
        "alignLevel": null
      },
      "type": "graph"
    },
    {
      "aliasColors": {},
      "id": 402,
      "bars": false,
      "dashLength": 10,
      "dashes": false,
      "datasource": null,
      "fieldConfig": {
        "defaults": {
          "custom": {}
        },
        "overrides": []
      },
      "fill": 1,
      "fillGradient": 0,
      "hiddenSeries": false,
      "legend": {
        "avg": false,
        "current": false,
        "max": false,
        "min": false,
        "show": true,
        "total": false,
        "values": false
      },
      "lines": true,
      "linewidth": 1,
      "nullPointMode": "null",
      "options": {
        "alertThreshold": true
      },
      "percentage": false,
      "pluginVersion": "7.3.3",
      "pointradius": 2,
      "points": false,
      "renderer": "flot",
      "seriesOverrides": [],
      "spaceLength": 10,
      "stack": false,
      "steppedLine": false,
      "description": "single_cluster_monitor",
      "gridPos": {
        "h": 9,
        "w": 12
      },
      "targets": [
        {
          "expr": "kafka_monitor_commit_latency_service_single_cluster_monitor_commit_offset_latency_ms_99th",
          "interval": "",
          "legendFormat": "commit_offset_latency_ms_99th",
          "refId": "Kdw"
        }
      ],
      "title": "commit_latency_service",
      "thresholds": [],
      "timeFrom": null,
      "timeRegions": [],
      "timeShift": null,
      "tooltip": {
        "shared": true,
        "sort": 0,
        "value_type": "individual"
      },
      "xaxis": {
        "buckets": null,
        "mode": "time",
        "name": null,
        "show": true,
        "values": []
      },
      "yaxis": {
        "align": false,
        "alignLevel": null
      },
      "type": "graph"
    },
    {
      "aliasColors": {},
      "id": 89,
      "bars": false,
      "dashLength": 10,
      "dashes": false,
      "datasource": null,
      "fieldConfig": {
        "defaults": {
          "custom": {}
        },
        "overrides": []
      },
      "fill": 1,
      "fillGradient": 0,
      "hiddenSeries": false,
      "legend": {
        "avg": false,
        "current": false,
        "max": false,
        "min": false,
        "show": true,
        "total": false,
        "values": false
      },
      "lines": true,
      "linewidth": 1,
      "nullPointMode": "null",
      "options": {
        "alertThreshold": true
      },
      "percentage": false,
      "pluginVersion": "7.3.3",
      "pointradius": 2,
      "points": false,
      "renderer": "flot",
      "seriesOverrides": [],
      "spaceLength": 10,
      "stack": false,
      "steppedLine": false,
      "description": "single_cluster_monitor",
      "gridPos": {
        "h": 9,
        "w": 12
      },
      "targets": [
        {
          "expr": "kafka_monitor_commit_latency_service_single_cluster_monitor_commit_offset_latency_ms_avg",
          "interval": "",
          "legendFormat": "commit_offset_latency_ms_avg",
          "refId": "ghL"
        }
      ],
      "title": "commit_latency_service",
      "thresholds": [],
      "timeFrom": null,
      "timeRegions": [],
      "timeShift": null,
      "tooltip": {
        "shared": true,
        "sort": 0,
        "value_type": "individual"
      },
      "xaxis": {
        "buckets": null,
        "mode": "time",
        "name": null,
        "show": true,
        "values": []
      },
      "yaxis": {
        "align": false,
        "alignLevel": null
      },
      "type": "graph"
    },
    {
      "aliasColors": {},
      "id": 130,
      "bars": false,
      "dashLength": 10,
      "dashes": false,
      "datasource": null,
      "fieldConfig": {
        "defaults": {
          "custom": {}
        },
        "overrides": []
      },
      "fill": 1,
      "fillGradient": 0,
      "hiddenSeries": false,
      "legend": {
        "avg": false,
        "current": false,
        "max": false,
        "min": false,
        "show": true,
        "total": false,
        "values": false
      },
      "lines": true,
      "linewidth": 1,
      "nullPointMode": "null",
      "options": {
        "alertThreshold": true
      },
      "percentage": false,
      "pluginVersion": "7.3.3",
      "pointradius": 2,
      "points": false,
      "renderer": "flot",
      "seriesOverrides": [],
      "spaceLength": 10,
      "stack": false,
      "steppedLine": false,
      "description": "single_cluster_monitor",
      "gridPos": {
        "h": 9,
        "w": 12
      },
      "targets": [
        {
          "expr": "kafka_monitor_commit_latency_service_single_cluster_monitor_commit_offset_latency_ms_max",
          "interval": "",
          "legendFormat": "commit_offset_latency_ms_max",
          "refId": "PCj"
        }
      ],
      "title": "commit_latency_service",
      "thresholds": [],
      "timeFrom": null,
      "timeRegions": [],
      "timeShift": null,
      "tooltip": {
        "shared": true,
        "sort": 0,
        "value_type": "individual"
      },
      "xaxis": {
        "buckets": null,
        "mode": "time",
        "name": null,
        "show": true,
        "values": []
      },
      "yaxis": {
        "align": false,
        "alignLevel": null
      },
      "type": "graph"
    }
  ],
  "schemaVersion": 26,
  "style": "dark",
  "tags": [],
  "templating": {
    "list": []
  },
  "time": {
    "from": "now-6h",
    "to": "now"
  },
  "timepicker": {},
  "timezone": "",
  "title": "Commit Latency",
  "thresholds": [],
  "timeFrom": null,
  "timeRegions": [],
  "timeShift": null,
  "tooltip": {
    "shared": true,
    "sort": 0,
    "value_type": "individual"
  },
  "xaxis": {
    "buckets": null,
    "mode": "time",
    "name": null,
    "show": true,
    "values": []
  },
  "yaxis": {
    "align": false,
    "alignLevel": null
  },
  "version": 1
}